LICENSE
MANIFEST.in
README.md
requirements.txt
setup.cfg
setup.py
wxnat/__init__.py
wxnat/__main__.py
wxnat/browser.py
wxnat/icons.py
wxnat/assets/file.png
wxnat/assets/folder_loaded.png
wxnat/assets/folder_unloaded.png
wxnatpy.egg-info/PKG-INFO
wxnatpy.egg-info/SOURCES.txt
wxnatpy.egg-info/dependency_links.txt
wxnatpy.egg-info/requires.txt
wxnatpy.egg-info/top_level.txt