Metadata-Version: 1.1
Name: wxnatpy
Version: 0.3.1
Summary: wxPython XNAT repository browser
Home-page: https://github.com/pauldmccarthy/wxnatpy
Author: Paul McCarthy
Author-email: pauldmccarthy@gmail.com
License: Apache License Version 2.0
Platform: UNKNOWN
Classifier: Development Status :: 3 - Alpha
Classifier: Intended Audience :: Developers
Classifier: License :: OSI Approved :: Apache Software License
Classifier: Programming Language :: Python :: 2.7
Classifier: Programming Language :: Python :: 3.5
Classifier: Topic :: Software Development :: Libraries :: Python Modules
